{"years": [2013, 2014, 2015, 2016, 2017, 2018, 2019, 2020, 2021, 2022, 2023], "startArticleYear": 2019, "endArticleYear": 2022, "startPatentYear": 2017, "endPatentYear": 2020, "groups": {"sp500": {"cset_id": 1000500, "name": "S&P 500", "articles": {"highly_cited": {"total": 22, "counts": [2, 2, 2, 2, 2, 2, 2, 2, 2, 2, 2]}, "all_publications": {"total": 65989, "counts": [6140, 6201, 6156, 6350, 6316, 6286, 6492, 6513, 6121, 4655, 4760]}, "ai_publications": {"total": 202, "counts": [11, 12, 12, 13, 15, 20, 25, 29, 30, 19, 16]}, "ai_publications_growth": {"total": 0, "counts": []}, "ai_pubs_top_conf": {"total": 74, "counts": [3, 3, 4, 4, 6, 8, 11, 10, 14, 7, 3]}, "citation_counts": {"total": 9791, "counts": [118, 171, 237, 321, 446, 683, 987, 1346, 1703, 1833, 1945]}, "cv_pubs": {"total": 52, "counts": [3, 3, 3, 4, 4, 5, 6, 7, 7, 6, 4]}, "nlp_pubs": {"total": 38, "counts": [2, 2, 2, 3, 3, 4, 5, 6, 6, 3, 1]}, "robotics_pubs": {"total": 14, "counts": [1, 1, 1, 1, 1, 1, 1, 2, 2, 2, 1]}, "citations_per_article": {"total": 19, "counts": [3, 4, 5, 6, 8, 11, 14, 17, 22, 36, 55]}}, "patents": {"ai_patents": {"total": 188, "counts": [5, 7, 9, 15, 22, 30, 32, 33, 31, 4, 0]}, "ai_patents_growth": {"total": 15, "counts": []}, "ai_patents_grants": {"total": 107, "counts": []}, "all_patents": {"total": 1880, "counts": [50, 67, 91, 146, 223, 297, 321, 330, 314, 39, 1]}, "Physical_Sciences_and_Engineering": {"total": 7, "counts": [0, 0, 0, 1, 1, 1, 1, 1, 1, 0, 0]}, "Life_Sciences": {"total": 18, "counts": [0, 1, 1, 1, 2, 3, 3, 3, 3, 0, 0]}, "Security__eg_cybersecurity": {"total": 12, "counts": [0, 0, 0, 1, 1, 2, 2, 2, 2, 0, 0]}, "Transportation": {"total": 18, "counts": [0, 0, 1, 2, 3, 4, 3, 2, 2, 0, 0]}, "Industrial_and_Manufacturing": {"total": 6, "counts": [0, 0, 0, 0, 1, 1, 1, 1, 1, 0, 0]}, "Education": {"total": 2, "counts": [0, 0, 0, 0, 0, 0, 0, 0, 0, 0, 0]}, "Document_Mgt_and_Publishing": {"total": 0, "counts": [0, 0, 0, 0, 0, 0, 0, 0, 0, 0, 0]}, "Military": {"total": 0, "counts": [0, 0, 0, 0, 0, 0, 0, 0, 0, 0, 0]}, "Agricultural": {"total": 2, "counts": [0, 0, 0, 0, 0, 0, 0, 1, 0, 0, 0]}, "Computing_in_Government": {"total": 1, "counts": [0, 0, 0, 0, 0, 0, 0, 0, 0, 0, 0]}, "Personal_Devices_and_Computing": {"total": 106, "counts": [2, 3, 5, 8, 13, 18, 20, 20, 16, 2, 0]}, "Banking_and_Finance": {"total": 7, "counts": [0, 0, 0, 0, 1, 1, 1, 1, 1, 0, 0]}, "Telecommunications": {"total": 39, "counts": [1, 1, 2, 3, 5, 7, 7, 7, 6, 1, 0]}, "Networks__eg_social_IOT_etc": {"total": 4, "counts": [0, 0, 0, 1, 1, 1, 0, 1, 0, 0, 0]}, "Business": {"total": 25, "counts": [1, 1, 1, 3, 4, 4, 4, 4, 3, 0, 0]}, "Energy_Management": {"total": 3, "counts": [0, 0, 0, 0, 0, 0, 0, 0, 0, 0, 0]}, "Entertainment": {"total": 1, "counts": [0, 0, 0, 0, 0, 0, 0, 0, 0, 0, 0]}, "Nanotechnology": {"total": 0, "counts": [0, 0, 0, 0, 0, 0, 0, 0, 0, 0, 0]}, "Semiconductors": {"total": 2, "counts": [0, 0, 0, 0, 0, 0, 0, 0, 0, 0, 0]}, "Language_Processing": {"total": 6, "counts": [0, 1, 1, 1, 2, 1, 0, 0, 0, 0, 0]}, "Speech_Processing": {"total": 10, "counts": [0, 0, 0, 1, 1, 2, 2, 2, 1, 0, 0]}, "Knowledge_Representation": {"total": 22, "counts": [1, 1, 1, 2, 4, 4, 4, 3, 3, 0, 0]}, "Planning_and_Scheduling": {"total": 17, "counts": [1, 1, 1, 2, 2, 3, 3, 3, 2, 0, 0]}, "Control": {"total": 23, "counts": [1, 1, 1, 3, 4, 4, 4, 3, 2, 0, 0]}, "Distributed_AI": {"total": 2, "counts": [0, 0, 0, 0, 0, 0, 0, 0, 0, 0, 0]}, "Robotics": {"total": 0, "counts": [0, 0, 0, 0, 0, 0, 0, 0, 0, 0, 0]}, "Computer_Vision": {"total": 33, "counts": [1, 1, 1, 3, 5, 6, 5, 5, 5, 1, 0]}, "Analytics_and_Algorithms": {"total": 15, "counts": [0, 0, 1, 1, 1, 2, 3, 3, 3, 0, 0]}, "Measuring_and_Testing": {"total": 17, "counts": [0, 0, 1, 1, 2, 3, 3, 3, 2, 0, 0]}}, "other_metrics": {"tt1_jobs": {"total": 5324, "counts": null}, "ai_jobs": {"total": 418, "counts": null}}}, "global500": {"cset_id": 1000501, "name": "Fortune Global 500", "articles": {"highly_cited": {"total": 43, "counts": [4, 4, 4, 4, 4, 4, 4, 4, 4, 4, 4]}, "all_publications": {"total": 176294, "counts": [16058, 15940, 15945, 16589, 16666, 16891, 17452, 17626, 17001, 13144, 12983]}, "ai_publications": {"total": 530, "counts": [26, 28, 30, 33, 38, 50, 65, 76, 80, 55, 48]}, "ai_publications_growth": {"total": 14, "counts": []}, "ai_pubs_top_conf": {"total": 164, "counts": [7, 7, 9, 9, 12, 18, 25, 24, 31, 15, 7]}, "citation_counts": {"total": 21262, "counts": [273, 390, 531, 711, 977, 1475, 2128, 2897, 3677, 3978, 4225]}, "cv_pubs": {"total": 141, "counts": [8, 8, 9, 9, 10, 13, 16, 19, 20, 16, 14]}, "nlp_pubs": {"total": 86, "counts": [4, 5, 5, 5, 6, 9, 12, 14, 15, 7, 4]}, "robotics_pubs": {"total": 54, "counts": [3, 3, 4, 4, 4, 5, 6, 7, 7, 6, 5]}, "citations_per_article": {"total": 37, "counts": [7, 10, 12, 14, 18, 24, 30, 36, 46, 73, 99]}}, "patents": {"ai_patents": {"total": 559, "counts": [12, 16, 22, 37, 59, 83, 101, 105, 102, 23, 0]}, "ai_patents_growth": {"total": 55, "counts": []}, "ai_patents_grants": {"total": 276, "counts": []}, "all_patents": {"total": 5589, "counts": [118, 161, 223, 365, 588, 827, 1007, 1048, 1022, 228, 3]}, "Physical_Sciences_and_Engineering": {"total": 16, "counts": [1, 0, 1, 1, 2, 2, 3, 3, 3, 1, 0]}, "Life_Sciences": {"total": 50, "counts": [1, 2, 2, 4, 6, 8, 10, 9, 8, 1, 0]}, "Security__eg_cybersecurity": {"total": 30, "counts": [0, 1, 1, 2, 3, 5, 6, 6, 5, 1, 0]}, "Transportation": {"total": 60, "counts": [1, 2, 3, 6, 9, 11, 12, 9, 7, 1, 0]}, "Industrial_and_Manufacturing": {"total": 21, "counts": [0, 0, 0, 1, 2, 3, 5, 4, 3, 1, 0]}, "Education": {"total": 5, "counts": [0, 0, 0, 0, 1, 1, 1, 1, 1, 0, 0]}, "Document_Mgt_and_Publishing": {"total": 0, "counts": [0, 0, 0, 0, 0, 0, 0, 0, 0, 0, 0]}, "Military": {"total": 0, "counts": [0, 0, 0, 0, 0, 0, 0, 0, 0, 0, 0]}, "Agricultural": {"total": 5, "counts": [0, 0, 0, 0, 1, 1, 1, 1, 1, 0, 0]}, "Computing_in_Government": {"total": 1, "counts": [0, 0, 0, 0, 0, 0, 0, 0, 0, 0, 0]}, "Personal_Devices_and_Computing": {"total": 280, "counts": [5, 8, 11, 18, 31, 44, 53, 55, 47, 9, 0]}, "Banking_and_Finance": {"total": 19, "counts": [0, 0, 1, 1, 2, 3, 4, 4, 4, 1, 0]}, "Telecommunications": {"total": 107, "counts": [2, 3, 4, 7, 13, 18, 20, 20, 18, 2, 0]}, "Networks__eg_social_IOT_etc": {"total": 9, "counts": [0, 1, 1, 1, 2, 1, 1, 1, 1, 0, 0]}, "Business": {"total": 67, "counts": [2, 2, 3, 6, 8, 10, 11, 12, 10, 3, 0]}, "Energy_Management": {"total": 23, "counts": [1, 1, 1, 1, 2, 3, 4, 4, 5, 3, 0]}, "Entertainment": {"total": 4, "counts": [0, 0, 0, 0, 0, 1, 1, 1, 1, 0, 0]}, "Nanotechnology": {"total": 1, "counts": [0, 0, 0, 0, 0, 0, 0, 0, 0, 0, 0]}, "Semiconductors": {"total": 5, "counts": [0, 0, 0, 0, 1, 1, 1, 1, 1, 0, 0]}, "Language_Processing": {"total": 12, "counts": [1, 1, 2, 3, 4, 2, 0, 0, 0, 0, 0]}, "Speech_Processing": {"total": 28, "counts": [1, 1, 1, 2, 3, 5, 6, 5, 4, 1, 0]}, "Knowledge_Representation": {"total": 50, "counts": [2, 2, 3, 4, 8, 9, 8, 7, 6, 1, 0]}, "Planning_and_Scheduling": {"total": 47, "counts": [1, 2, 2, 4, 6, 7, 8, 9, 7, 2, 0]}, "Control": {"total": 76, "counts": [1, 2, 4, 7, 12, 14, 15, 11, 8, 1, 0]}, "Distributed_AI": {"total": 3, "counts": [0, 0, 0, 0, 0, 1, 1, 1, 0, 0, 0]}, "Robotics": {"total": 0, "counts": [0, 0, 0, 0, 0, 0, 0, 0, 0, 0, 0]}, "Computer_Vision": {"total": 100, "counts": [1, 2, 3, 8, 14, 18, 16, 17, 16, 3, 0]}, "Analytics_and_Algorithms": {"total": 44, "counts": [1, 1, 2, 2, 4, 6, 8, 9, 9, 2, 0]}, "Measuring_and_Testing": {"total": 51, "counts": [1, 1, 2, 4, 6, 8, 10, 10, 8, 1, 0]}}, "other_metrics": {"tt1_jobs": {"total": 11004, "counts": null}, "ai_jobs": {"total": 866, "counts": null}}}}, "groupIdOffset": 1000000}